Metadata-Version: 2.1
Name: odoo8-addon-account-banking-pain-base
Version: 8.0.0.4.1.99.dev2
Summary: Base module for PAIN file generation
Home-page: https://github.com/OCA/bank-payment
Author: Akretion, Noviat, Serv. Tecnol. Avanzados - Pedro M. Baeza, Antiun Ingeniería S.L., Odoo Community Association (OCA)
Author-email: support@odoo-community.org
License: AGPL-3
Platform: UNKNOWN
Classifier: Programming Language :: Python
Classifier: Framework :: Odoo
Classifier: Framework :: Odoo :: 8.0
Classifier: License :: OSI Approved :: GNU Affero General Public License v3
Requires-Python: ~=2.7
Requires-Dist: lxml
Requires-Dist: odoo8-addon-account-banking-payment-export
Requires-Dist: odoo (<9.0a,>=8.0a)
Requires-Dist: unidecode
